converter/__init__.py
converter/fields_converter.py
etl_converter_talenttech-1.2.9.dist-info/LICENSE.txt
etl_converter_talenttech-1.2.9.dist-info/METADATA
etl_converter_talenttech-1.2.9.dist-info/WHEEL
etl_converter_talenttech-1.2.9.dist-info/top_level.txt
etl_converter_talenttech-1.2.9.dist-info/RECORD
