Metadata-Version: 2.1
Name: etl-converter-talenttech
Version: 1.2.9
Summary: TopMind ETL converter
Home-page: https://github.com/severgroup-tt/topmind-commons/py/etl-converter
Author: Dmitry Utiralov
Author-email: d.utiralov@talenttech.ru
License: MIT
Platform: UNKNOWN
Classifier: Programming Language :: Python :: 3
Classifier: License :: OSI Approved :: MIT License
Classifier: Operating System :: OS Independent
Requires-Python: >=3.6
Requires-Dist: sqlalchemy
Requires-Dist: clickhouse-sqlalchemy
Requires-Dist: sqlalchemy-vertica-python
Requires-Dist: psycopg2-binary
